<?xml version="1.0" encoding="UTF-8"?>
<gmd:MD_Metadata xmlns:gmd="http://www.isotc211.org/2005/gmd"
                 xmlns:xsi="http://www.w3.org/2001/XMLSchema-instance"
                 xmlns:gts="http://www.isotc211.org/2005/gts"
                 xmlns:gco="http://www.isotc211.org/2005/gco"
                 xmlns:gml="http://www.opengis.net/gml"
                 xmlns:geonet="http://www.fao.org/geonetwork"
                 xsi:schemaLocation="http://www.isotc211.org/2005/gmd http://lab7.betech.virginia.edu:8080/geonetwork/xml/schemas/iso19139/schema.xsd">
  <gmd:fileIdentifier>
      <gco:CharacterString xmlns:srv="http://www.isotc211.org/2005/srv">3a2a9aeb-72ea-44e4-adb1-b6a12488dd2c</gco:CharacterString>
  </gmd:fileIdentifier>
  <gmd:language>
      <gco:CharacterString>eng</gco:CharacterString>
  </gmd:language>
  <gmd:characterSet>
      <gmd:MD_CharacterSetCode codeListValue="utf8"
                               codeList="http://www.isotc211.org/2005/resources/codeList.xml#MD_CharacterSetCode"/>
  </gmd:characterSet>
  <gmd:contact>
      <gmd:CI_ResponsibleParty>
         <gmd:individualName>
            <gco:CharacterString>Wendy Robertson</gco:CharacterString>
         </gmd:individualName>
         <gmd:organisationName>
            <gco:CharacterString>Scholars' Lab, University of Virginia</gco:CharacterString>
         </gmd:organisationName>
         <gmd:positionName>
            <gco:CharacterString>Staff</gco:CharacterString>
         </gmd:positionName>
         <gmd:contactInfo>
            <gmd:CI_Contact>
               <gmd:phone>
                  <gmd:CI_Telephone>
                     <gmd:voice>
                        <gco:CharacterString>1-434-243-8800</gco:CharacterString>
                     </gmd:voice>
                  </gmd:CI_Telephone>
               </gmd:phone>
               <gmd:address>
                  <gmd:CI_Address>
                     <gmd:deliveryPoint>
                        <gco:CharacterString>Alderman Library</gco:CharacterString>
                     </gmd:deliveryPoint>
                     <gmd:city>
                        <gco:CharacterString>Charlottesville</gco:CharacterString>
                     </gmd:city>
                     <gmd:administrativeArea>
                        <gco:CharacterString>Virginia</gco:CharacterString>
                     </gmd:administrativeArea>
                     <gmd:postalCode>
                        <gco:CharacterString>22902</gco:CharacterString>
                     </gmd:postalCode>
                     <gmd:country>
                        <gco:CharacterString>USA</gco:CharacterString>
                     </gmd:country>
                     <gmd:electronicMailAddress gco:nilReason="missing">
                        <gco:CharacterString/>
                     </gmd:electronicMailAddress>
                  </gmd:CI_Address>
               </gmd:address>
            </gmd:CI_Contact>
         </gmd:contactInfo>
         <gmd:role>
            <gmd:CI_RoleCode codeListValue="pointOfContact"
                             codeList="http://www.isotc211.org/2005/resources/codeList.xml#CI_RoleCode"/>
         </gmd:role>
      </gmd:CI_ResponsibleParty>
  </gmd:contact>
  <gmd:dateStamp>
      <gco:DateTime xmlns:srv="http://www.isotc211.org/2005/srv">2009-07-07T15:25:28</gco:DateTime>
  </gmd:dateStamp>
  <gmd:metadataStandardName>
      <gco:CharacterString xmlns:srv="http://www.isotc211.org/2005/srv">ISO 19115:2003/19139</gco:CharacterString>
  </gmd:metadataStandardName>
  <gmd:metadataStandardVersion>
      <gco:CharacterString xmlns:srv="http://www.isotc211.org/2005/srv">1.0</gco:CharacterString>
  </gmd:metadataStandardVersion>
  <gmd:identificationInfo>
      <gmd:MD_DataIdentification>
         <gmd:citation>
            <gmd:CI_Citation>
               <gmd:title>
                  <gco:CharacterString>South Africa  Datastack</gco:CharacterString>
               </gmd:title>
               <gmd:date>
                  <gmd:CI_Date>
                     <gmd:date>
                        <gco:DateTime>2009-07-07T00:00:00</gco:DateTime>
                     </gmd:date>
                     <gmd:dateType>
                        <gmd:CI_DateTypeCode codeListValue="publication"
                                             codeList="http://www.isotc211.org/2005/resources/codeList.xml#CI_DateTypeCode"/>
                     </gmd:dateType>
                  </gmd:CI_Date>
               </gmd:date>
               <gmd:edition gco:nilReason="missing">
                  <gco:CharacterString/>
               </gmd:edition>
               <gmd:presentationForm>
                  <gmd:CI_PresentationFormCode codeListValue="mapDigital"
                                               codeList="http://www.isotc211.org/2005/resources/codeList.xml#CI_PresentationFormCode"/>
               </gmd:presentationForm>
               <gmd:presentationForm>
                  <gmd:CI_PresentationFormCode codeList="http://www.isotc211.org/2005/resources/codeList.xml#CI_PresentationFormCode"
                                               codeListValue=""/>
               </gmd:presentationForm>
            </gmd:CI_Citation>
         </gmd:citation>
         <gmd:abstract>
            <gco:CharacterString>This collection (stacked series) of datasets is provided *as is* by Geocommons to UVA Library’s Scholars’ Lab. 
* // * No original metadata was provided with this dataset; thus information about its provenance, spatial detail, temporal extent, and upkeep are unknown* // * Datasets/Layers
                    included in this datastack (with non-exclusive list of included attributes): *
                    ponet_polygon  * dnnet_polygon  * clline_arc  * rdline_arc * tsline_arc * utline_arc * aepoint_point * popoint_point 
* // * These data were made available to the University of Virginia for educational and research uses only.
 Access is restricted to students, faculty and staff of the University of Virginia.</gco:CharacterString>
         </gmd:abstract>
         <gmd:purpose gco:nilReason="missing">
            <gco:CharacterString/>
         </gmd:purpose>
         <gmd:status>
            <gmd:MD_ProgressCode codeListValue="completed"
                                 codeList="http://www.isotc211.org/2005/resources/codeList.xml#MD_ProgressCode"/>
         </gmd:status>
         <gmd:pointOfContact>
            <gmd:CI_ResponsibleParty>
               <gmd:individualName>
                  <gco:CharacterString>Scholar's Lab</gco:CharacterString>
               </gmd:individualName>
               <gmd:organisationName>
                  <gco:CharacterString>University of Virginia</gco:CharacterString>
               </gmd:organisationName>
               <gmd:positionName>
                  <gco:CharacterString>Staff</gco:CharacterString>
               </gmd:positionName>
               <gmd:contactInfo>
                  <gmd:CI_Contact>
                     <gmd:phone>
                        <gmd:CI_Telephone>
                           <gmd:voice>
                              <gco:CharacterString>1-434-243-8800</gco:CharacterString>
                           </gmd:voice>
                           <gmd:facsimile gco:nilReason="missing">
                              <gco:CharacterString/>
                           </gmd:facsimile>
                        </gmd:CI_Telephone>
                     </gmd:phone>
                     <gmd:address>
                        <gmd:CI_Address>
                           <gmd:deliveryPoint>
                              <gco:CharacterString>Alderman Library</gco:CharacterString>
                           </gmd:deliveryPoint>
                           <gmd:city>
                              <gco:CharacterString>Charlottesville</gco:CharacterString>
                           </gmd:city>
                           <gmd:administrativeArea>
                              <gco:CharacterString>Virginia</gco:CharacterString>
                           </gmd:administrativeArea>
                           <gmd:postalCode>
                              <gco:CharacterString>22902</gco:CharacterString>
                           </gmd:postalCode>
                           <gmd:country>
                              <gco:CharacterString>USA</gco:CharacterString>
                           </gmd:country>
                           <gmd:electronicMailAddress gco:nilReason="missing">
                              <gco:CharacterString/>
                           </gmd:electronicMailAddress>
                        </gmd:CI_Address>
                     </gmd:address>
                     <gmd:onlineResource>
                        <gmd:CI_OnlineResource>
                           <gmd:linkage>
                              <gmd:URL>http://www2.lib.virginia.edu/scholarslab/</gmd:URL>
                           </gmd:linkage>
                           <gmd:protocol>
                              <gco:CharacterString>WWW:LINK-1.0-http--link</gco:CharacterString>
                           </gmd:protocol>
                           <gmd:name>
                              <gco:CharacterString>The Scholar's Lab at the
                                            University of Virginia (website)</gco:CharacterString>
                           </gmd:name>
                           <gmd:description>
                              <gco:CharacterString>The Scholar's Lab at the                                             University of Virginia (website)</gco:CharacterString>
                           </gmd:description>
                        </gmd:CI_OnlineResource>
                     </gmd:onlineResource>
                  </gmd:CI_Contact>
               </gmd:contactInfo>
               <gmd:role>
                  <gmd:CI_RoleCode codeList="http://www.isotc211.org/2005/resources/codeList.xml#CI_RoleCode"
                                   codeListValue="pointOfContact"/>
               </gmd:role>
            </gmd:CI_ResponsibleParty>
         </gmd:pointOfContact>
         <gmd:resourceMaintenance>
            <gmd:MD_MaintenanceInformation>
               <gmd:maintenanceAndUpdateFrequency>
                  <gmd:MD_MaintenanceFrequencyCode codeListValue="notPlanned"
                                                   codeList="http://www.isotc211.org/2005/resources/codeList.xml#MD_MaintenanceFrequencyCode"/>
               </gmd:maintenanceAndUpdateFrequency>
            </gmd:MD_MaintenanceInformation>
         </gmd:resourceMaintenance>
         <gmd:graphicOverview>
            <gmd:MD_BrowseGraphic>
               <gmd:fileName gco:nilReason="missing">
                  <gco:CharacterString/>
               </gmd:fileName>
               <gmd:fileDescription>
                  <gco:CharacterString>thumbnail</gco:CharacterString>
               </gmd:fileDescription>
            </gmd:MD_BrowseGraphic>
         </gmd:graphicOverview>
         <gmd:graphicOverview>
            <gmd:MD_BrowseGraphic>
               <gmd:fileName gco:nilReason="missing">
                  <gco:CharacterString/>
               </gmd:fileName>
               <gmd:fileDescription>
                  <gco:CharacterString>large_thumbnail</gco:CharacterString>
               </gmd:fileDescription>
            </gmd:MD_BrowseGraphic>
         </gmd:graphicOverview>
         <gmd:descriptiveKeywords>
            <gmd:MD_Keywords>
               <gmd:keyword>
                  <gco:CharacterString>airports</gco:CharacterString>
               </gmd:keyword>
               <gmd:keyword>
                  <gco:CharacterString>administrative boundary</gco:CharacterString>
               </gmd:keyword>
               <gmd:keyword>
                  <gco:CharacterString>roads</gco:CharacterString>
               </gmd:keyword>
               <gmd:keyword>
                  <gco:CharacterString>hydrology</gco:CharacterString>
               </gmd:keyword>
               <gmd:keyword>
                  <gco:CharacterString>railroad</gco:CharacterString>
               </gmd:keyword>
               <gmd:keyword>
                  <gco:CharacterString>transportation</gco:CharacterString>
               </gmd:keyword>
               <gmd:keyword>
                  <gco:CharacterString>utility</gco:CharacterString>
               </gmd:keyword>
               <gmd:keyword>
                  <gco:CharacterString>landmarks</gco:CharacterString>
               </gmd:keyword>
               <gmd:type>
                  <gmd:MD_KeywordTypeCode codeListValue="theme"
                                          codeList="http://www.isotc211.org/2005/resources/codeList.xml#MD_KeywordTypeCode"/>
               </gmd:type>
            </gmd:MD_Keywords>
         </gmd:descriptiveKeywords>
         <gmd:descriptiveKeywords>
            <gmd:MD_Keywords>
               <gmd:keyword>
                  <gco:CharacterString>South Africa</gco:CharacterString>
               </gmd:keyword>
               <gmd:type>
                  <gmd:MD_KeywordTypeCode codeListValue="place"
                                          codeList="http://www.isotc211.org/2005/resources/codeList.xml#MD_KeywordTypeCode"/>
               </gmd:type>
            </gmd:MD_Keywords>
         </gmd:descriptiveKeywords>
         <gmd:resourceConstraints>
            <gmd:MD_LegalConstraints>
               <gmd:accessConstraints>
                  <gmd:MD_RestrictionCode codeListValue="otherRestrictions"
                                          codeList="http://www.isotc211.org/2005/resources/codeList.xml#MD_RestrictionCode"/>
               </gmd:accessConstraints>
               <gmd:useConstraints>
                  <gmd:MD_RestrictionCode codeListValue="otherRestrictions"
                                          codeList="http://www.isotc211.org/2005/resources/codeList.xml#MD_RestrictionCode"/>
               </gmd:useConstraints>
               <gmd:otherConstraints>
                  <gco:CharacterString>UVA on-grounds access only</gco:CharacterString>
               </gmd:otherConstraints>
            </gmd:MD_LegalConstraints>
         </gmd:resourceConstraints>
         <gmd:spatialRepresentationType>
            <gmd:MD_SpatialRepresentationTypeCode codeListValue="vector"
                                                  codeList="http://www.isotc211.org/2005/resources/codeList.xml#MD_SpatialRepresentationTypeCode"/>
         </gmd:spatialRepresentationType>
         <gmd:language>
            <gco:CharacterString>eng</gco:CharacterString>
         </gmd:language>
         <gmd:characterSet>
            <gmd:MD_CharacterSetCode codeListValue="utf8"
                                     codeList="http://www.isotc211.org/2005/resources/codeList.xml#MD_CharacterSetCode"/>
         </gmd:characterSet>
         <gmd:topicCategory>
            <gmd:MD_TopicCategoryCode>boundaries</gmd:MD_TopicCategoryCode>
         </gmd:topicCategory>
         <gmd:topicCategory>
            <gmd:MD_TopicCategoryCode>transportation</gmd:MD_TopicCategoryCode>
         </gmd:topicCategory>
         <gmd:topicCategory>
            <gmd:MD_TopicCategoryCode>utilitiesCommunication</gmd:MD_TopicCategoryCode>
         </gmd:topicCategory>
         <gmd:topicCategory>
            <gmd:MD_TopicCategoryCode>environment</gmd:MD_TopicCategoryCode>
         </gmd:topicCategory>
         <gmd:extent>
            <gmd:EX_Extent>
               <gmd:temporalElement>
                  <gmd:EX_TemporalExtent>
                     <gmd:extent>
                        <gml:TimePeriod gml:id="default-temporal-extent">
                           <gml:beginPosition>2000-02-01T13:00:00</gml:beginPosition>
                           <gml:endPosition>2000-02-29T13:00:00</gml:endPosition>
                        </gml:TimePeriod>
                     </gmd:extent>
                  </gmd:EX_TemporalExtent>
               </gmd:temporalElement>
            </gmd:EX_Extent>
         </gmd:extent>
         <gmd:extent>
            <gmd:EX_Extent>
               <gmd:geographicElement>
                  <gmd:EX_GeographicBoundingBox>
                     <gmd:westBoundLongitude>
                        <gco:Decimal>14.40</gco:Decimal>
                     </gmd:westBoundLongitude>
                     <gmd:eastBoundLongitude>
                        <gco:Decimal>36.25</gco:Decimal>
                     </gmd:eastBoundLongitude>
                     <gmd:southBoundLatitude>
                        <gco:Decimal>-35.5</gco:Decimal>
                     </gmd:southBoundLatitude>
                     <gmd:northBoundLatitude>
                        <gco:Decimal>-19.5</gco:Decimal>
                     </gmd:northBoundLatitude>
                  </gmd:EX_GeographicBoundingBox>
               </gmd:geographicElement>
            </gmd:EX_Extent>
         </gmd:extent>
         <gmd:supplementalInformation gco:nilReason="missing">
            <gco:CharacterString/>
         </gmd:supplementalInformation>
      </gmd:MD_DataIdentification>
  </gmd:identificationInfo>
  <gmd:distributionInfo>
      <gmd:MD_Distribution>
         <gmd:distributor>
            <gmd:MD_Distributor>
               <gmd:distributorContact>
                  <gmd:CI_ResponsibleParty>
                     <gmd:organisationName>
                        <gco:CharacterString>the University of Virginia                                 Library</gco:CharacterString>
                     </gmd:organisationName>
                     <gmd:role>
                        <gmd:CI_RoleCode codeList="http://www.isotc211.org/2005/resources/codeList.xml#CI_RoleCode"
                                         codeListValue="distributor"/>
                     </gmd:role>
                  </gmd:CI_ResponsibleParty>
               </gmd:distributorContact>
               <gmd:distributorFormat>
                  <gmd:MD_Format>
                     <gmd:name>
                        <gmd:MD_MediumNameCode codeList="http://www.isotc211.org/2005/resources/codeList.xml#MD_MediumNameCode"
                                               codeListValue="onLine"/>
                     </gmd:name>
                     <gmd:version gco:nilReason="missing">
                        <gco:CharacterString/>
                     </gmd:version>
                  </gmd:MD_Format>
               </gmd:distributorFormat>
            </gmd:MD_Distributor>
         </gmd:distributor>
         <gmd:transferOptions>
            <gmd:MD_DigitalTransferOptions>
               <gmd:onLine>
                  <gmd:CI_OnlineResource>
                     <gmd:linkage>
                        <gmd:URL>http://gis.lib.virginia.edu/ows/Geography/World/SouthAfrica/wms</gmd:URL>
                     </gmd:linkage>
                     <gmd:protocol>
                        <gco:CharacterString>OGC:WMS-1.1.1-http-get-map</gco:CharacterString>
                     </gmd:protocol>
                     <gmd:name>
                        <gco:CharacterString>UVA Geoserver WMS : South Africa Datastack</gco:CharacterString>
                     </gmd:name>
                     <gmd:description>
                        <gco:CharacterString>UVA Geoserver WMS : South Africa Datastack</gco:CharacterString>
                     </gmd:description>
                  </gmd:CI_OnlineResource>
               </gmd:onLine>
               <gmd:onLine>
                  <gmd:CI_OnlineResource>
                     <gmd:linkage>
                        <gmd:URL>http://gis.lib.virginia.edu/ows/Geography/World/SouthAfrica/wfs</gmd:URL>
                     </gmd:linkage>
                     <gmd:protocol>
                        <gco:CharacterString>OGC:WFS-1.0.0-http-get-capabilities</gco:CharacterString>
                     </gmd:protocol>
                     <gmd:name>
                        <gco:CharacterString>UVA Geoserver WFS :South Africa Datastack                                 Datastack</gco:CharacterString>
                     </gmd:name>
                     <gmd:description>
                        <gco:CharacterString>UVA Geoserver WFS : South Africa  Datastack                                Datastack</gco:CharacterString>
                     </gmd:description>
                  </gmd:CI_OnlineResource>
               </gmd:onLine>
               <gmd:onLine>
                  <gmd:CI_OnlineResource>
                     <gmd:linkage xmlns:srv="http://www.isotc211.org/2005/srv">
                        <gmd:URL>http://gis.lib.virginia.edu/ows/wms</gmd:URL>
                     </gmd:linkage>
                     <gmd:protocol>
                        <gco:CharacterString>OGC:WMS-1.1.1-http-get-capabilities</gco:CharacterString>
                     </gmd:protocol>
                     <gmd:name>
                        <gco:CharacterString>SouthAfrica:popoint_point</gco:CharacterString>
                     </gmd:name>
                     <gmd:description>
                        <gco:CharacterString>population centers (point)</gco:CharacterString>
                     </gmd:description>
                  </gmd:CI_OnlineResource>
               </gmd:onLine>
               <gmd:onLine>
                  <gmd:CI_OnlineResource>
                     <gmd:linkage xmlns:srv="http://www.isotc211.org/2005/srv">
                        <gmd:URL>http://gis.lib.virginia.edu/ows/wms</gmd:URL>
                     </gmd:linkage>
                     <gmd:protocol>
                        <gco:CharacterString>OGC:WMS-1.1.1-http-get-capabilities</gco:CharacterString>
                     </gmd:protocol>
                     <gmd:name>
                        <gco:CharacterString>SouthAfrica:aepoint_point</gco:CharacterString>
                     </gmd:name>
                     <gmd:description>
                        <gco:CharacterString>airports (point)</gco:CharacterString>
                     </gmd:description>
                  </gmd:CI_OnlineResource>
               </gmd:onLine>
               <gmd:onLine>
                  <gmd:CI_OnlineResource>
                     <gmd:linkage>
                        <gmd:URL>http://gis.lib.virginia.edu/ows/wms</gmd:URL>
                     </gmd:linkage>
                     <gmd:protocol>
                        <gco:CharacterString>OGC:WMS-1.1.1-http-get-capabilities</gco:CharacterString>
                     </gmd:protocol>
                     <gmd:name>
                        <gco:CharacterString>SouthAfrica:utline_arc</gco:CharacterString>
                     </gmd:name>
                     <gmd:description>
                        <gco:CharacterString>utility lines</gco:CharacterString>
                     </gmd:description>
                  </gmd:CI_OnlineResource>
               </gmd:onLine>
               <gmd:onLine>
                  <gmd:CI_OnlineResource>
                     <gmd:linkage>
                        <gmd:URL>http://gis.lib.virginia.edu/ows/wms</gmd:URL>
                     </gmd:linkage>
                     <gmd:protocol>
                        <gco:CharacterString>OGC:WMS-1.1.1-http-get-capabilities</gco:CharacterString>
                     </gmd:protocol>
                     <gmd:name>
                        <gco:CharacterString>SouthAfrica:tsline_arc</gco:CharacterString>
                     </gmd:name>
                     <gmd:description>
                        <gco:CharacterString>train lines</gco:CharacterString>
                     </gmd:description>
                  </gmd:CI_OnlineResource>
               </gmd:onLine>
               <gmd:onLine>
                  <gmd:CI_OnlineResource>
                     <gmd:linkage>
                        <gmd:URL>http://gis.lib.virginia.edu/ows/wms</gmd:URL>
                     </gmd:linkage>
                     <gmd:protocol>
                        <gco:CharacterString>OGC:WMS-1.1.1-http-get-capabilities</gco:CharacterString>
                     </gmd:protocol>
                     <gmd:name>
                        <gco:CharacterString>SouthAfrica:rdline_arc</gco:CharacterString>
                     </gmd:name>
                     <gmd:description>
                        <gco:CharacterString>roads (line)</gco:CharacterString>
                     </gmd:description>
                  </gmd:CI_OnlineResource>
               </gmd:onLine>
               <gmd:onLine>
                  <gmd:CI_OnlineResource>
                     <gmd:linkage>
                        <gmd:URL>http://gis.lib.virginia.edu/ows/wms</gmd:URL>
                     </gmd:linkage>
                     <gmd:protocol>
                        <gco:CharacterString>OGC:WMS-1.1.1-http-get-capabilities</gco:CharacterString>
                     </gmd:protocol>
                     <gmd:name>
                        <gco:CharacterString>SouthAfrica:cline_arc</gco:CharacterString>
                     </gmd:name>
                     <gmd:description>
                        <gco:CharacterString>cultural landmarks (line)</gco:CharacterString>
                     </gmd:description>
                  </gmd:CI_OnlineResource>
               </gmd:onLine>
               <gmd:onLine>
                  <gmd:CI_OnlineResource>
                     <gmd:linkage>
                        <gmd:URL>http://gis.lib.virginia.edu/ows/wms</gmd:URL>
                     </gmd:linkage>
                     <gmd:protocol>
                        <gco:CharacterString>OGC:WMS-1.1.1-http-get-capabilities</gco:CharacterString>
                     </gmd:protocol>
                     <gmd:name>
                        <gco:CharacterString>SouthAfrica:dnnet_polygon</gco:CharacterString>
                     </gmd:name>
                     <gmd:description>
                        <gco:CharacterString>drainage network (polygon)</gco:CharacterString>
                     </gmd:description>
                  </gmd:CI_OnlineResource>
               </gmd:onLine>
               <gmd:onLine>
                  <gmd:CI_OnlineResource>
                     <gmd:linkage>
                        <gmd:URL>http://gis.lib.virginia.edu/ows/wms</gmd:URL>
                     </gmd:linkage>
                     <gmd:protocol>
                        <gco:CharacterString>OGC:WMS-1.1.1-http-get-capabilities</gco:CharacterString>
                     </gmd:protocol>
                     <gmd:name>
                        <gco:CharacterString>SouthAfrica:ponet_polygon</gco:CharacterString>
                     </gmd:name>
                     <gmd:description>
                        <gco:CharacterString>population network (polygon)</gco:CharacterString>
                     </gmd:description>
                  </gmd:CI_OnlineResource>
               </gmd:onLine>
            </gmd:MD_DigitalTransferOptions>
         </gmd:transferOptions>
      </gmd:MD_Distribution>
  </gmd:distributionInfo>
</gmd:MD_Metadata>